ppcommons/__init__.py
ppcommons/bos.py
ppcommons/cli.py
ppcommons/helpers.py
ppcommons/init.py
PPCommons-0.0.3.dist-info/LICENCE
PPCommons-0.0.3.dist-info/METADATA
PPCommons-0.0.3.dist-info/WHEEL
PPCommons-0.0.3.dist-info/entry_points.txt
PPCommons-0.0.3.dist-info/top_level.txt
PPCommons-0.0.3.dist-info/RECORD
